[
    {
        "TEST_FLAG": "NONE",
        "COMMENT": "OpenJ9 JDK 8 release configuration - only differences from base. JDK 8 doesn't support aarch64_mac",
        "DEFAULT_TEST_TARGETS": "sanity.functional,extended.functional,special.functional,sanity.openjdk,extended.openjdk,special.openjdk,sanity.system,extended.system,special.system,sanity.perf,extended.perf,sanity.jck,extended.jck,special.jck",
        "DEFAULT_FIPS_TEST_TARGETS": "extended.functional,sanity.openjdk,extended.openjdk,sanity.jck,extended.jck,special.jck",
        "DEFAULT_FIPS140_2_TEST_TARGETS": "sanity.openjdk,extended.openjdk,sanity.jck,extended.jck,special.jck",
        "PLATFORM_TARGETS": [
            { "aarch64_linux": "defaultTestTargets" },
            { "ppc64_aix": "defaultTestTargets" },
            { "ppc64le_linux": "defaultTestTargets" },
            { "s390x_linux": "defaultTestTargets" },
            { "x86-64_linux": "defaultTestTargets" },
            { "x86-64_mac": "defaultTestTargets" },
            { "x86-64_windows": "defaultTestTargets" },
            { "x86-32_windows": "defaultTestTargets" }
        ]
    },
    {
        "TEST_FLAG": "FIPS140_3_OpenJCEPlusFIPS",
        "PLATFORM_TARGETS": [
            { "aarch64_linux": "defaultFipsTestTargets" },
            { "ppc64_aix": "defaultFipsTestTargets" },
            { "ppc64le_linux": "defaultFipsTestTargets" },
            { "s390x_linux": "defaultFipsTestTargets" },
            { "x86-64_linux": "defaultFipsTestTargets" },
            { "x86-64_mac": "defaultFipsTestTargets" },
            { "x86-64_windows": "defaultFipsTestTargets" }
        ]
    },
    {
        "TEST_FLAG": "FIPS140_3_OpenJCEPlusFIPS.FIPS140-3",
        "PLATFORM_TARGETS": [
            { "aarch64_linux": "defaultFipsTestTargets" },
            { "ppc64_aix": "defaultFipsTestTargets" },
            { "ppc64le_linux": "defaultFipsTestTargets" },
            { "s390x_linux": "defaultFipsTestTargets" },
            { "x86-64_linux": "defaultFipsTestTargets" },
            { "x86-64_mac": "defaultFipsTestTargets" },
            { "x86-64_windows": "defaultFipsTestTargets" }
        ]
    },
    {
        "TEST_FLAG": "FIPS140_3_OpenJCEPlusFIPS.FIPS140-3-Strongly-Enforced",
        "PLATFORM_TARGETS": [
            { "aarch64_linux": "defaultFipsTestTargets" },
            { "ppc64_aix": "defaultFipsTestTargets" },
            { "ppc64le_linux": "defaultFipsTestTargets" },
            { "s390x_linux": "defaultFipsTestTargets" },
            { "x86-64_linux": "defaultFipsTestTargets" },
            { "x86-64_mac": "defaultFipsTestTargets" },
            { "x86-64_windows": "defaultFipsTestTargets" }
        ]
    },
    {
        "TEST_FLAG": "FIPS140_2",
        "PLATFORM_TARGETS": [
            { "ppc64le_linux": "defaultFips140_2TestTargets" },
            { "s390x_linux": "defaultFips140_2TestTargets" },
            { "x86-64_linux": "defaultFips140_2TestTargets" }
        ]
    }
]
